django_bird_autoconf/__init__.py
django_bird_autoconf/plugin.py
django_bird_autoconf/py.typed
django_bird_autoconf-0.1.1.dist-info/METADATA
django_bird_autoconf-0.1.1.dist-info/WHEEL
django_bird_autoconf-0.1.1.dist-info/entry_points.txt
django_bird_autoconf-0.1.1.dist-info/licenses/LICENSE
django_bird_autoconf-0.1.1.dist-info/RECORD
