Metadata-Version: 2.4
Name: django-bird-autoconf
Version: 0.1.1
Summary: django-bird plugin for autoconfiguring your Django project
Project-URL: Documentation, https://github.com/joshuadavidthomas/django-bird-autoconf#readme
Project-URL: Issues, https://github.com/joshuadavidthomas/django-bird-autoconf/issues
Project-URL: Source, https://github.com/joshuadavidthomas/django-bird-autoconf
Author-email: Josh <josh@joshthomas.dev>
License: MIT License
License-File: LICENSE
Classifier: Development Status :: 4 - Beta
Classifier: Environment :: Plugins
Classifier: Framework :: Django
Classifier: Framework :: Django :: 4.2
Classifier: Framework :: Django :: 5.0
Classifier: Framework :: Django :: 5.1
Classifier: Framework :: Django :: 5.2
Classifier: Framework :: Setuptools Plugin
Classifier: License :: OSI Approved :: MIT License
Classifier: Operating System :: OS Independent
Classifier: Programming Language :: Python
Classifier: Programming Language :: Python :: 3
Classifier: Programming Language :: Python :: 3 :: Only
Classifier: Programming Language :: Python :: 3.10
Classifier: Programming Language :: Python :: 3.11
Classifier: Programming Language :: Python :: 3.12
Classifier: Programming Language :: Python :: 3.13
Classifier: Programming Language :: Python :: Implementation :: CPython
Requires-Python: >=3.10
Requires-Dist: django-bird>=0.16.2
